deeptrees/__init__.py
deeptrees/inference.py
deeptrees/pretrained.py
deeptrees/dataloading/__init__.py
deeptrees/dataloading/datamodule.py
deeptrees/dataloading/datasets.py
deeptrees/dataloading/preprocessing.py
deeptrees/datasets/__init__.py
deeptrees/datasets/halleDOP20.py
deeptrees/model/__init__.py
deeptrees/model/deeptrees_model.py
deeptrees/model/distance_model.py
deeptrees/model/inference_model.py
deeptrees/model/segmentation_model.py
deeptrees/modules/__init__.py
deeptrees/modules/indices.py
deeptrees/modules/losses.py
deeptrees/modules/metrics.py
deeptrees/modules/polygon_metrics.py
deeptrees/modules/polygon_utils.py
deeptrees/modules/postprocessing.py
deeptrees/modules/rasterize_utils.py
deeptrees/modules/traits.py
deeptrees/modules/utils.py
deeptrees-1.8.2.dist-info/LICENSE
deeptrees-1.8.2.dist-info/METADATA
deeptrees-1.8.2.dist-info/WHEEL
deeptrees-1.8.2.dist-info/top_level.txt
deeptrees-1.8.2.dist-info/RECORD
