Metadata-Version: 2.1
Name: deeptrees
Version: 1.8.2
Summary: Tree crown segmentation and analysis in remote sensing imagery with PyTorch
Home-page: https://codebase.helmholtz.cloud/taimur.khan/DeepTrees
Author: Taimur Khan, Caroline Arnold, Harsh Grover
Author-email: taimur.khan@ufz.de
License: MIT
Keywords: tree-crowns,pytorch,remote-sensing,deep-learning,semantic-segmentation,vegetation-ecology,instance-segmentation,active-learning
Classifier: Programming Language :: Python
Classifier: Programming Language :: Python :: 3
Classifier: Programming Language :: Python :: Implementation :: CPython
Classifier: Programming Language :: Python :: Implementation :: PyPy
Requires-Python: >=3.10.0
License-File: LICENSE
Requires-Dist: torch==2.4.0
Requires-Dist: numpy==1.26.0
Requires-Dist: segmentation-models-pytorch==0.3.3
Requires-Dist: torchvision>=0.19
Requires-Dist: torchmetrics>=1.6
Requires-Dist: xarray==2022.3.0
Requires-Dist: rasterio==1.4a3
Requires-Dist: rioxarray==0.17.0
Requires-Dist: shapely==2.0.5
Requires-Dist: scipy==1.14.0
Requires-Dist: scikit-image==0.24.0
Requires-Dist: hyperopt==0.2.7
Requires-Dist: fiona==1.9.6
Requires-Dist: psutil==6.0.0
Requires-Dist: geojson==3.1.0
Requires-Dist: geoplot==0.5.1
Requires-Dist: folium==0.17.0
Requires-Dist: hydra-core==1.3
Requires-Dist: lightning==2.4.0
Requires-Dist: onnx==1.16.2
Requires-Dist: rootutils>=1.0
Requires-Dist: rich>=13.0
Requires-Dist: mlflow==2.18.0
Requires-Dist: ipykernel
Requires-Dist: jsonschema2md>=1.3
Provides-Extra: test
Requires-Dist: pytest; extra == "test"
